pympcxx.cpython-312-x86_64-linux-gnu.so
pympcxx-0.7.1.dist-info/METADATA
pympcxx-0.7.1.dist-info/WHEEL
pympcxx-0.7.1.dist-info/top_level.txt
pympcxx-0.7.1.dist-info/RECORD
