Metadata-Version: 2.1
Name: pympcxx
Version: 0.7.1
Summary: MPC++ bindings for Python
Author: Nicola Piccinelli
License: MIT
